brokers/__init__.py
brokers/agent.py
brokers/consumer.py
brokers/producer.py
brokers_agents-0.1.dist-info/METADATA
brokers_agents-0.1.dist-info/WHEEL
brokers_agents-0.1.dist-info/top_level.txt
brokers_agents-0.1.dist-info/RECORD
