Metadata-Version: 2.1
Name: brokers-agents
Version: 0.1
Summary: Paquete de brokers para manejo de colas de RabbitMQ
Home-page: https://github.com/arielespinosa/BrokerMessageAgent
Author: Ossuan
Author-email: ossuan.lugo@gmail.com
Classifier: Programming Language :: Python :: 3
Classifier: License :: OSI Approved :: MIT License
Classifier: Operating System :: OS Independent
Requires-Python: >=3.8
